westpy/__init__.py
westpy/atom.py
westpy/dataContainer.py
westpy/electronicStructure.py
westpy/geometry.py
westpy/groundState.py
westpy/session.py
westpy/units.py
westpy/utils.py
westpy-3.1.1.dist-info/METADATA
westpy-3.1.1.dist-info/RECORD
westpy-3.1.1.dist-info/WHEEL
westpy-3.1.1.dist-info/top_level.txt
westpy-3.1.1.dist-info/zip-safe
